api_management_local/__init__.py
api_management_local/api_call.py
api_management_local/api_limit.py
api_management_local/api_limit_status.py
api_management_local/api_management_local.py
api_management_local/api_mangement_manager.py
api_management_local/api_type.py
api_management_local/constants.py
api_management_local/direct.py
api_management_local/exception_api.py
api_management_local/indirect.py
api_management_local/utils.py
api_management_local-0.0.80.dist-info/METADATA
api_management_local-0.0.80.dist-info/WHEEL
api_management_local-0.0.80.dist-info/top_level.txt
api_management_local-0.0.80.dist-info/RECORD
