Metadata-Version: 2.1
Name: api-management-local
Version: 0.0.80
Summary: PyPI Package for Circles api-management-local-python-package
Home-page: https://github.com/circles-zone/api-management-local-python-package
Author: Circles
Author-email: info@circlez.ai
Classifier: Programming Language :: Python :: 3
Classifier: License :: Other/Proprietary License
Classifier: Operating System :: OS Independent
Requires-Dist: requests >=2.31.0
Requires-Dist: database-mysql-local >=0.0.306
Requires-Dist: logger-local >=0.0.135
Requires-Dist: python-sdk-remote >=0.0.93
Requires-Dist: star-local >=0.0.16
Requires-Dist: url-remote >=0.0.91
